django_plugin_kolo/__init__.py
django_plugin_kolo-0.1.dist-info/LICENSE
django_plugin_kolo-0.1.dist-info/METADATA
django_plugin_kolo-0.1.dist-info/WHEEL
django_plugin_kolo-0.1.dist-info/entry_points.txt
django_plugin_kolo-0.1.dist-info/top_level.txt
django_plugin_kolo-0.1.dist-info/RECORD
