Metadata-Version: 2.1
Name: django-plugin-kolo
Version: 0.1
Summary: Makes integrating kolo even easier
Author: Fabian Binz
License: Apache-2.0
Project-URL: Homepage, https://github.com/fbinz/django-plugin-kolo
Project-URL: Changelog, https://github.com/fbinz/django-plugin-kolo/releases
Project-URL: Issues, https://github.com/fbinz/django-plugin-kolo/issues
Project-URL: CI, https://github.com/fbinz/django-plugin-kolo/actions
Classifier: License :: OSI Approved :: Apache Software License
License-File: LICENSE
Requires-Dist: django
Requires-Dist: djp
Requires-Dist: kolo>=2.34.2
Provides-Extra: test
Requires-Dist: pytest; extra == "test"
Requires-Dist: pytest-django; extra == "test"
